COPYING
MANIFEST.in
README.rst
buildout.cfg
develop.cfg
environment.yml
requirements.txt
setup.py
version.txt
bob/__init__.py
bob.paper.taslp_2017.egg-info/PKG-INFO
bob.paper.taslp_2017.egg-info/SOURCES.txt
bob.paper.taslp_2017.egg-info/dependency_links.txt
bob.paper.taslp_2017.egg-info/entry_points.txt
bob.paper.taslp_2017.egg-info/not-zip-safe
bob.paper.taslp_2017.egg-info/requires.txt
bob.paper.taslp_2017.egg-info/top_level.txt
bob/paper/__init__.py
bob/paper/taslp_2017/__init__.py
bob/paper/taslp_2017/algorithm/__init__.py
bob/paper/taslp_2017/algorithm/lda.py
bob/paper/taslp_2017/config/__init__.py
bob/paper/taslp_2017/config/database/__init__.py
bob/paper/taslp_2017/config/database/asvspoof_cm.py
bob/paper/taslp_2017/config/database/avspoof.py
bob/paper/taslp_2017/config/database/avspoof_logical.py
bob/paper/taslp_2017/config/database/avspoof_physical.py
bob/paper/taslp_2017/config/extractor/__init__.py
bob/paper/taslp_2017/config/extractor/mean_spectrum_256ms_shift_10ms.py
bob/paper/taslp_2017/config/extractor/mean_spectrum_32ms_shift_10ms.py
bob/paper/taslp_2017/config/extractor/mean_std_spectrum_128ms_shift_10ms.py
bob/paper/taslp_2017/config/extractor/mean_std_spectrum_16ms_shift_10ms.py
bob/paper/taslp_2017/config/extractor/mean_std_spectrum_256ms_shift_10ms.py
bob/paper/taslp_2017/config/extractor/mean_std_spectrum_32ms_shift_10ms.py
bob/paper/taslp_2017/config/extractor/mean_std_spectrum_512ms_shift_10ms.py
bob/paper/taslp_2017/config/extractor/mean_std_spectrum_64ms_shift_10ms.py
bob/paper/taslp_2017/config/extractor/std_spectrum_256ms_shift_10ms.py
bob/paper/taslp_2017/config/extractor/std_spectrum_32ms_shift_10ms.py
bob/paper/taslp_2017/config/grid/__init__.py
bob/paper/taslp_2017/config/grid/normal.py
bob/paper/taslp_2017/config/preprocessor/__init__.py
bob/paper/taslp_2017/config/preprocessor/energy_2gauss_remove_head_tail.py
bob/paper/taslp_2017/config/preprocessor/no_preprocessing.py
bob/paper/taslp_2017/database/__init__.py
bob/paper/taslp_2017/database/asvspoof.py
bob/paper/taslp_2017/database/avspoof.py
bob/paper/taslp_2017/database/database.py
bob/paper/taslp_2017/extractor/SpectralStatistics.py
bob/paper/taslp_2017/extractor/__init__.py
bob/paper/taslp_2017/preprocessor/Energy_2Gauss_Remove_Head_Tail.py
