Metadata-Version: 1.1
Name: bob.paper.taslp-2017
Version: 1.0.12
Summary: Presentation Attack Detection Using Long Term Spectral Statistics for Trustworthy Speaker Verification
Home-page: https://gitlab.idiap.ch/bob/bob.paper.taslp_2017
Author: Hannah Muckenhirn
Author-email: hannah.muckenhirn@idiap.ch
License: GPLv3
Keywords: presentation attack detection,speaker verification,long term spectral statistics
Platform: UNKNOWN
Classifier: Framework :: Bob
Classifier: Development Status :: 4 - Beta
Classifier: Intended Audience :: Developers
Classifier: License :: OSI Approved :: GNU General Public License v3 (GPLv3)
Classifier: Natural Language :: English
Classifier: Programming Language :: Python
Classifier: Topic :: Scientific/Engineering :: Artificial Intelligence
